AFL/agent/AcquisitionFunction.py
AFL/agent/AgentClient.py
AFL/agent/DowShampoo_SampleDriver.py
AFL/agent/EI_AcquisitionFunction.py
AFL/agent/GaussianProcess.py
AFL/agent/HscedGaussianProcess.py
AFL/agent/Metric.py
AFL/agent/Multimodal_AL_SampleDriver.py
AFL/agent/Multimodal_AgentDriver.py
AFL/agent/PhaseLabeler.py
AFL/agent/PhaseMap.py
AFL/agent/PhaseMap_pandas.py
AFL/agent/SANS_AL_SampleDriver.py
AFL/agent/SAS_AL_SampleDriver.py
AFL/agent/SAS_AgentDriver.py
AFL/agent/SAS_Grid_AL_SampleDriver.py
AFL/agent/SAXS_AL_SampleDriver.py
AFL/agent/UCB_AcquisitionFunction.py
AFL/agent/WatchDog.py
AFL/agent/reduce_usaxs.py
AFL/agent/util.py
AFL/agent/vSAS_NoDeck_AL_SampleDriver.py
AFL/agent/xarray_extensions.py
AFL/agent/virtual_AL/Virtual_MultiModal_AL_SampleDriver.py
AFL/agent/virtual_AL/Virtual_MultiModal_AgentDriver.py
AFL/agent/virtual_AL/vSAS_AL_SampleDriver.py
AFL/agent/virtual_AL/vSAS_AgentDriver.py
AFL/agent/widgets/ALPlot.py
AFL/agent/widgets/DiffractionLabeler.py
AFL/agent/widgets/MPLDiffractionLabeler.py
AFL/agent/widgets/__init__.py
AFL/double_agent/AcquisitionFunction.py
AFL/double_agent/AgentDriver.py
AFL/double_agent/AutoSAS.py
AFL/double_agent/AutoSASWidget.py
AFL/double_agent/AutoSAS_Driver.py
AFL/double_agent/Boundary.py
AFL/double_agent/Extrapolator.py
AFL/double_agent/Generator.py
AFL/double_agent/Labeler.py
AFL/double_agent/MaskGrid.py
AFL/double_agent/PairMetric.py
AFL/double_agent/Pipeline.py
AFL/double_agent/PipelineContext.py
AFL/double_agent/PipelineOp.py
AFL/double_agent/Preprocessor.py
AFL/double_agent/TensorFlowExtrapolator.py
AFL/double_agent/__init__.py
AFL/double_agent/_version.py
AFL/double_agent/plotting.py
AFL/double_agent/util.py
AFL/double_agent/xarray_extensions.py
AFL/double_agent/data/README.md
AFL/double_agent/data/__init__.py
AFL/double_agent/data/example_dataset.nc
AFL/double_agent/data/synthetic_sans.nc
AFL/double_agent/prefab/__init__.py
AFL/double_agent/prefab/find_boundaries.json
AFL/double_agent/prefab/preprocess.json
afl_agent-1.3.1.dist-info/METADATA
afl_agent-1.3.1.dist-info/WHEEL
afl_agent-1.3.1.dist-info/licenses/LICENSE
afl_agent-1.3.1.dist-info/RECORD
