Metadata-Version: 2.4
Name: AFL-agent
Version: 1.3.1
Summary: Agent code for the Autonomous Formulation Lab
Author: Peter A. Beaucage, Duncan R. Sutherland
Author-email: "Tyler B. Martin" <tyler.martin@nist.gov>
License: NIST License
License-File: LICENSE
Classifier: Programming Language :: Python :: 3
Classifier: Programming Language :: Python :: 3.11
Requires-Python: >=3.11
Requires-Dist: anywidget
Requires-Dist: bottleneck
Requires-Dist: bumps
Requires-Dist: kaleido
Requires-Dist: matplotlib
Requires-Dist: mpltern
Requires-Dist: netcdf4
Requires-Dist: numpy
Requires-Dist: pandas
Requires-Dist: periodictable
Requires-Dist: pillow
Requires-Dist: pint
Requires-Dist: plotly
Requires-Dist: pyepics
Requires-Dist: sasdata
Requires-Dist: sasmodels
Requires-Dist: scikit-image
Requires-Dist: scikit-learn
Requires-Dist: scipy
Requires-Dist: seaborn
Requires-Dist: shapely
Requires-Dist: sympy
Requires-Dist: tiled[all]
Requires-Dist: tqdm
Requires-Dist: xarray
Requires-Dist: zeroconf
Provides-Extra: all
Requires-Dist: black; extra == 'all'
Requires-Dist: bokeh; extra == 'all'
Requires-Dist: flask-cors; extra == 'all'
Requires-Dist: flask-jwt-extended>=4.0; extra == 'all'
Requires-Dist: flask<2.3; extra == 'all'
Requires-Dist: gpflow; extra == 'all'
Requires-Dist: ipympl; extra == 'all'
Requires-Dist: ipywidgets; extra == 'all'
Requires-Dist: isort; extra == 'all'
Requires-Dist: jupyter; extra == 'all'
Requires-Dist: jupyterlab; extra == 'all'
Requires-Dist: markupsafe; extra == 'all'
Requires-Dist: mypy; extra == 'all'
Requires-Dist: nodejs; extra == 'all'
Requires-Dist: pydata-sphinx-theme; extra == 'all'
Requires-Dist: pyserial; extra == 'all'
Requires-Dist: pytest; extra == 'all'
Requires-Dist: requests; extra == 'all'
Requires-Dist: sphinx; extra == 'all'
Requires-Dist: sphinx-autosummary-accessors; extra == 'all'
Requires-Dist: sphinx-copybutton; extra == 'all'
Requires-Dist: sphinx-rtd-theme; extra == 'all'
Requires-Dist: sphinxcontrib-apidoc; extra == 'all'
Requires-Dist: sphinxcontrib-napoleon; extra == 'all'
Requires-Dist: tensorflow>=2.7; extra == 'all'
Requires-Dist: torch; extra == 'all'
Requires-Dist: torchvision; extra == 'all'
Requires-Dist: watchdog; extra == 'all'
Provides-Extra: automation
Requires-Dist: bokeh; extra == 'automation'
Requires-Dist: flask-cors; extra == 'automation'
Requires-Dist: flask-jwt-extended>=4.0; extra == 'automation'
Requires-Dist: flask<2.3; extra == 'automation'
Requires-Dist: markupsafe; extra == 'automation'
Requires-Dist: pyserial; extra == 'automation'
Requires-Dist: requests; extra == 'automation'
Requires-Dist: watchdog; extra == 'automation'
Provides-Extra: dev
Requires-Dist: black; extra == 'dev'
Requires-Dist: isort; extra == 'dev'
Requires-Dist: mypy; extra == 'dev'
Requires-Dist: pydata-sphinx-theme; extra == 'dev'
Requires-Dist: pytest; extra == 'dev'
Requires-Dist: sphinx; extra == 'dev'
Requires-Dist: sphinx-autosummary-accessors; extra == 'dev'
Requires-Dist: sphinx-copybutton; extra == 'dev'
Requires-Dist: sphinx-rtd-theme; extra == 'dev'
Requires-Dist: sphinxcontrib-apidoc; extra == 'dev'
Requires-Dist: sphinxcontrib-napoleon; extra == 'dev'
Provides-Extra: graph
Requires-Dist: pygraphviz; extra == 'graph'
Provides-Extra: jupyter
Requires-Dist: ipympl; extra == 'jupyter'
Requires-Dist: ipywidgets; extra == 'jupyter'
Requires-Dist: jupyter; extra == 'jupyter'
Requires-Dist: jupyterlab; extra == 'jupyter'
Requires-Dist: nodejs; extra == 'jupyter'
Provides-Extra: pytorch
Requires-Dist: torch; extra == 'pytorch'
Requires-Dist: torchvision; extra == 'pytorch'
Provides-Extra: tensorflow
Requires-Dist: gpflow; extra == 'tensorflow'
Requires-Dist: tensorflow>=2.7; extra == 'tensorflow'
